cameo_big_query_log
