Metadata-Version: 2.1
Name: cameo-big-query-log
Version: 0.1.13
Summary: A package for logging data to Google BigQuery
Home-page: UNKNOWN
Author: bear
Author-email: panda1993127@gmail.com
License: UNKNOWN
Platform: UNKNOWN
Classifier: Programming Language :: Python :: 3
Classifier: License :: OSI Approved :: MIT License
Classifier: Operating System :: OS Independent
Requires-Python: >=3.6
